<service>
        <setup>
                <versionNumber>114</versionNumber>
                <modelName>STB-6500-UA</modelName>
                <priority>NORMAL</priority>
                <content>
                        <type>CH_MAP</type>
                        <subversionNumber>114</subversionNumber>
                        <data>EtereoCanalAzteca.tlx</data>
                        <frequency>1</frequency>
                        <programNum>5</programNum>
                        <cTag>5</cTag>
                </content>
        </setup>
        <setup>
                <versionNumber>113</versionNumber>
                <modelName>55US670H0UA</modelName>
                <priority>NORMAL</priority>
                <content>
                        <type>CH_MAP</type>
                        <subversionNumber>113</subversionNumber>
                        <data>EtereoCanalAzteca.tlx</data>
                        <frequency>1</frequency>
                        <programNum>5</programNum>
                        <cTag>5</cTag>
                </content>
        </setup>
        <setup>
                <versionNumber>115</versionNumber>
                <modelName>75US770H0UD</modelName>
                <priority>NORMAL</priority>
                <content>
                        <type>CH_MAP</type>
                        <subversionNumber>115</subversionNumber>
                        <data>EtereoCanalAzteca.tlx</data>
                        <frequency>1</frequency>
                        <programNum>5</programNum>
                        <cTag>5</cTag>
                </content>
        </setup>
   </service>
